adafruit_circuitpython_minimqtt-8.0.3.dist-info/licenses/LICENSE
adafruit_minimqtt/__init__.py
adafruit_minimqtt/adafruit_minimqtt.py
adafruit_minimqtt/matcher.py
adafruit_circuitpython_minimqtt-8.0.3.dist-info/METADATA
adafruit_circuitpython_minimqtt-8.0.3.dist-info/WHEEL
adafruit_circuitpython_minimqtt-8.0.3.dist-info/top_level.txt
adafruit_circuitpython_minimqtt-8.0.3.dist-info/RECORD
