Metadata-Version: 2.4
Name: adafruit-circuitpython-minimqtt
Version: 8.0.3
Summary: MQTT client library for CircuitPython
Author-email: Adafruit Industries <circuitpython@adafruit.com>
License: MIT
Project-URL: Homepage, https://github.com/adafruit/Adafruit_CircuitPython_MiniMQTT
Keywords: adafruit,blinka,circuitpython,micropython,minimqtt,mqtt,,client,,socket
Classifier: Intended Audience :: Developers
Classifier: Topic :: Software Development :: Libraries
Classifier: Topic :: Software Development :: Embedded Systems
Classifier: Topic :: System :: Hardware
Classifier: License :: OSI Approved :: MIT License
Classifier: Programming Language :: Python :: 3
License-File: LICENSE
Requires-Dist: Adafruit-Blinka
Requires-Dist: Adafruit-Circuitpython-ConnectionManager
Requires-Dist: adafruit-circuitpython-ticks
Provides-Extra: optional
Dynamic: license-file
